{
    "$schema": "http://json-schema.org/draft-04/schema#",
    "$ref": "#/definitions/Extending",
    "definitions": {
        "Extending": {
            "properties": {
                "adaptings": {
                    "items": {
                        "$ref": "#/definitions/semio.extension.adapter.v1.Adapting"
                    },
                    "type": "array",
                    "description": "A summary of all descriptions about the translator."
                },
                "convertings": {
                    "items": {
                        "$ref": "#/definitions/semio.extension.converter.v1.Converting"
                    },
                    "type": "array",
                    "description": "A summary of all descriptions about the converter."
                },
                "transformings": {
                    "items": {
                        "$ref": "#/definitions/semio.extension.transformer.v1.Transforming"
                    },
                    "type": "array",
                    "description": "A summary of all descriptions about the transformer."
                },
                "translatings": {
                    "items": {
                        "$ref": "#/definitions/semio.extension.translator.v1.Translating"
                    },
                    "type": "array",
                    "description": "A summary of all descriptions about the translator."
                }
            },
            "additionalProperties": true,
            "type": "object",
            "title": "Extending",
            "description": "A description of what the extension is extending."
        },
        "semio.extension.adapter.v1.Adapting": {
            "properties": {
                "platform_url": {
                    "type": "string",
                    "description": "A url for the platform that is adapted."
                }
            },
            "additionalProperties": true,
            "type": "object",
            "title": "Adapting",
            "description": "Description what an adapter is adapting to."
        },
        "semio.extension.converter.v1.Converting": {
            "properties": {
                "source_type_url": {
                    "type": "string"
                },
                "target_type_url": {
                    "type": "string"
                }
            },
            "additionalProperties": true,
            "type": "object",
            "title": "Converting",
            "description": "Description what a converter is converting."
        },
        "semio.extension.transformer.v1.Transforming": {
            "additionalProperties": true,
            "type": "object",
            "title": "Transforming",
            "description": "Description what a transformer is transforming."
        },
        "semio.extension.translator.v1.Translating": {
            "properties": {
                "type_url": {
                    "type": "string"
                }
            },
            "additionalProperties": true,
            "type": "object",
            "title": "Translating",
            "description": "Description what a translator is translating."
        }
    }
}